[
  {
    "player1": "A. Sabalenka",
    "player2": "N. Osaka",
    "court": "Manolo Santana Stadium",
    "date": "2026-04-27",
    "tour": "ATP/WTA"
  },
  {
    "player1": "L. Noskova",
    "player2": "C. Gauff",
    "court": "Manolo Santana Stadium",
    "date": "2026-04-27",
    "tour": "ATP/WTA"
  },
  {
    "player1": "T. Atmane",
    "player2": "A. Zverev",
    "court": "Manolo Santana Stadium",
    "date": "2026-04-27",
    "tour": "ATP/WTA"
  },
  {
    "player1": "B. Bencic",
    "player2": "H. Baptiste",
    "court": "Arantxa Sanchez Stadium",
    "date": "2026-04-27",
    "tour": "ATP/WTA"
  },
  {
    "player1": "M. Kostyuk",
    "player2": "C. Mcnally",
    "court": "Arantxa Sanchez Stadium",
    "date": "2026-04-27",
    "tour": "ATP/WTA"
  },
  {
    "player1": "K. Khachanov",
    "player2": "J. Mensik",
    "court": "Arantxa Sanchez Stadium",
    "date": "2026-04-27",
    "tour": "ATP/WTA"
  },
  {
    "player1": "A. Li",
    "player2": "L. Fernandez",
    "court": "Stadium 3",
    "date": "2026-04-27",
    "tour": "ATP/WTA"
  },
  {
    "player1": "S. Sierra",
    "player2": "K. Pliskova",
    "court": "Stadium 3",
    "date": "2026-04-27",
    "tour": "ATP/WTA"
  },
  {
    "player1": "M. Andreeva",
    "player2": "A. Bondar",
    "court": "Stadium 3",
    "date": "2026-04-27",
    "tour": "ATP/WTA"
  },
  {
    "player1": "A. Vallejo",
    "player2": "F. Cobolli",
    "court": "Stadium 3",
    "date": "2026-04-27",
    "tour": "ATP/WTA"
  },
  {
    "player1": "M. Skoch",
    "player2": "E. Perez",
    "court": "Court 4",
    "date": "2026-04-27",
    "tour": "ATP/WTA"
  },
  {
    "player1": "S. Kenin",
    "player2": "K. Boulter",
    "court": "Court 4",
    "date": "2026-04-27",
    "tour": "ATP/WTA"
  }
]